{
  "Varieties": [
    {
      "Kind": "Абрикос",
      "Code": 0,
      "Application": 0,
      "Name": "Айсберг",
      "Patent": 0,
      "Closed": "01.01.1970",
      "Reason": "Потомучто"
    },
    {
      "Kind": "Абрикос",
      "Code": 0,
      "Application": 0,
      "Name": "Алеша",
      "Patent": 0,
      "Closed": "01.01.1970",
      "Reason": "Потомучто"
    },
    {
      "Kind": "Абрикос",
      "Code": 0,
      "Application": 0,
      "Name": "Айсберг",
      "Patent": 0,
      "Closed": "01.01.1970",
      "Reason": "Потомучто"
    },
    {
      "Kind": "Абрикос",
      "Code": 0,
      "Application": 0,
      "Name": "Алеша",
      "Patent": 0,
      "Closed": "01.01.1970",
      "Reason": "Потомучто"
    },
    {
      "Kind": "Айва",
      "Code": 0,
      "Application": 0,
      "Name": "Нивушка",
      "Patent": 0,
      "Closed": "01.01.1970",
      "Reason": "Потомучто"
    },
    {
      "Kind": "Томат",
      "Code": 0,
      "Application": 0,
      "Name": "Айсберг",
      "Patent": 0,
      "Closed": "01.01.1970",
      "Reason": "Потомучто"
    }
  ]
}